xer2csv/XerToCsvConverter.py
xer2csv/__init__.py
xer2csv-1.0.5.dist-info/LICENSE
xer2csv-1.0.5.dist-info/METADATA
xer2csv-1.0.5.dist-info/WHEEL
xer2csv-1.0.5.dist-info/top_level.txt
xer2csv-1.0.5.dist-info/RECORD
