Metadata-Version: 2.1
Name: xer2csv
Version: 1.0.5
Summary: A simple XER to CSV converter
Home-page: https://github.com/constantintcacenco/xer-to-csv-converter
Author: Constantin Tcacenco
Author-email: constantin.tcacenco@gmail.com
License: MIT
Download-URL: https://github.com/constantintcacenco/xer-to-csv-converter
Keywords: csv,xer,converter
Platform: UNKNOWN
Classifier: License :: OSI Approved :: MIT License
Classifier: Programming Language :: Python :: 3
Classifier: Programming Language :: Python :: 3.7
Requires-Dist: pandas
